{"cameraMode":{"drawMode":0,"name":"Shaded","section":"Shading Mode"},"sceneLighting":true,"audioPlay":false,"sceneViewState":{"m_AlwaysRefresh":false,"showFog":true,"showSkybox":true,"showFlares":true,"showImageEffects":true,"showParticleSystems":true,"showVisualEffectGraphs":true,"m_FxEnabled":true},"in2DMode":false,"pivot":{"x":-0.6735376715660095,"y":0.286223828792572,"z":0.5868993401527405},"rotation":{"x":-0.24802060425281526,"y":0.3799225986003876,"z":-0.10650180280208588,"w":-0.8847628235816956},"size":6.607396125793457,"orthographic":false}